gchat/__init__.py
gchat/__main__.py
gchat/cli/__init__.py
gchat/cli/account.py
gchat/cli/app.py
gchat/cli/messages.py
gchat/cli/search.py
gchat/cli/spaces.py
gchat/core/__init__.py
gchat/core/accounts.py
gchat/core/auth.py
gchat/core/client.py
gchat/core/config.py
gchat/models/__init__.py
gchat/models/account.py
gchat/models/message.py
gchat/models/space.py
gchat/ui/__init__.py
gchat/ui/console.py
gchat/ui/prompts.py
gchat/ui/tables.py
gchat/utils/__init__.py
gchat/utils/errors.py
gchat/utils/network.py
gchat/utils/paths.py
gchat_cli-0.2.1.dist-info/METADATA
gchat_cli-0.2.1.dist-info/WHEEL
gchat_cli-0.2.1.dist-info/entry_points.txt
gchat_cli-0.2.1.dist-info/licenses/LICENSE
gchat_cli-0.2.1.dist-info/RECORD
