Metadata-Version: 2.4
Name: gchat-cli
Version: 0.2.1
Summary: Google Chat CLI - Send messages from the command line
Author: Chad Saunders
License-Expression: MIT
License-File: LICENSE
Keywords: chat,cli,google-chat,google-workspace,messaging
Classifier: Development Status :: 4 - Beta
Classifier: Environment :: Console
Classifier: Intended Audience :: Developers
Classifier: License :: OSI Approved :: MIT License
Classifier: Operating System :: OS Independent
Classifier: Programming Language :: Python :: 3
Classifier: Programming Language :: Python :: 3.11
Classifier: Programming Language :: Python :: 3.12
Classifier: Topic :: Communications :: Chat
Requires-Python: >=3.11
Requires-Dist: google-api-python-client>=2.0.0
Requires-Dist: google-auth-oauthlib>=1.0.0
Requires-Dist: google-auth>=2.0.0
Requires-Dist: questionary>=2.0.0
Requires-Dist: rich>=13.0.0
Requires-Dist: tomli-w>=1.0.0
Requires-Dist: typer>=0.9.0
Provides-Extra: dev
Requires-Dist: mypy>=1.0.0; extra == 'dev'
Requires-Dist: pytest-cov>=4.0.0; extra == 'dev'
Requires-Dist: pytest>=7.0.0; extra == 'dev'
Requires-Dist: ruff>=0.1.0; extra == 'dev'
